[
  {
    "ContainingType": "WebApi.Controllers.AppTypesController",
    "Method": "GetBookTypes",
    "RelativePath": "api/AppTypes/GetBookTypes",
    "HttpMethod": "GET",
    "IsController": true,
    "Order": 0,
    "Parameters": [],
    "ReturnTypes": []
  },
  {
    "ContainingType": "WebApi.Controllers.AppTypesController",
    "Method": "GetCities",
    "RelativePath": "api/AppTypes/GetCities",
    "HttpMethod": "GET",
    "IsController": true,
    "Order": 0,
    "Parameters": [],
    "ReturnTypes": []
  },
  {
    "ContainingType": "WebApi.Controllers.AppTypesController",
    "Method": "GetCountries",
    "RelativePath": "api/AppTypes/GetCountries",
    "HttpMethod": "GET",
    "IsController": true,
    "Order": 0,
    "Parameters": [],
    "ReturnTypes": []
  },
  {
    "ContainingType": "WebApi.Controllers.AppTypesController",
    "Method": "GetPublishers",
    "RelativePath": "api/AppTypes/GetPublishers",
    "HttpMethod": "GET",
    "IsController": true,
    "Order": 0,
    "Parameters": [],
    "ReturnTypes": []
  },
  {
    "ContainingType": "WebApi.Controllers.AppTypesController",
    "Method": "GetStates",
    "RelativePath": "api/AppTypes/GetStates",
    "HttpMethod": "GET",
    "IsController": true,
    "Order": 0,
    "Parameters": [],
    "ReturnTypes": []
  },
  {
    "ContainingType": "WebApi.Controllers.AuthorsController",
    "Method": "Create",
    "RelativePath": "api/Authors",
    "HttpMethod": "POST",
    "IsController": true,
    "Order": 0,
    "Parameters": [
      {
        "Name": "createModel",
        "Type": "WebApi.Models.Authors.CreateAuthor",
        "IsRequired": true
      }
    ],
    "ReturnTypes": []
  },
  {
    "ContainingType": "WebApi.Controllers.AuthorsController",
    "Method": "GetAll",
    "RelativePath": "api/Authors",
    "HttpMethod": "GET",
    "IsController": true,
    "Order": 0,
    "Parameters": [],
    "ReturnTypes": []
  },
  {
    "ContainingType": "WebApi.Controllers.AuthorsController",
    "Method": "Update",
    "RelativePath": "api/Authors",
    "HttpMethod": "PUT",
    "IsController": true,
    "Order": 0,
    "Parameters": [
      {
        "Name": "updateModel",
        "Type": "WebApi.Models.Authors.UpdateAuthor",
        "IsRequired": true
      }
    ],
    "ReturnTypes": []
  },
  {
    "ContainingType": "WebApi.Controllers.AuthorsController",
    "Method": "Delete",
    "RelativePath": "api/Authors/{Id}",
    "HttpMethod": "DELETE",
    "IsController": true,
    "Order": 0,
    "Parameters": [
      {
        "Name": "Id",
        "Type": "System.Int32",
        "IsRequired": true
      }
    ],
    "ReturnTypes": []
  },
  {
    "ContainingType": "WebApi.Controllers.AuthorsController",
    "Method": "Get",
    "RelativePath": "api/Authors/{Id}",
    "HttpMethod": "GET",
    "IsController": true,
    "Order": 0,
    "Parameters": [
      {
        "Name": "Id",
        "Type": "System.Int32",
        "IsRequired": true
      }
    ],
    "ReturnTypes": []
  },
  {
    "ContainingType": "WebApi.Controllers.BooksController",
    "Method": "Create",
    "RelativePath": "api/Books",
    "HttpMethod": "POST",
    "IsController": true,
    "Order": 0,
    "Parameters": [
      {
        "Name": "createModel",
        "Type": "WebApi.Models.Books.CreateBook",
        "IsRequired": true
      }
    ],
    "ReturnTypes": []
  },
  {
    "ContainingType": "WebApi.Controllers.BooksController",
    "Method": "GetAll",
    "RelativePath": "api/Books",
    "HttpMethod": "GET",
    "IsController": true,
    "Order": 0,
    "Parameters": [],
    "ReturnTypes": []
  },
  {
    "ContainingType": "WebApi.Controllers.BooksController",
    "Method": "Update",
    "RelativePath": "api/Books",
    "HttpMethod": "PUT",
    "IsController": true,
    "Order": 0,
    "Parameters": [
      {
        "Name": "updateModel",
        "Type": "WebApi.Models.Books.UpdateBook",
        "IsRequired": true
      }
    ],
    "ReturnTypes": []
  },
  {
    "ContainingType": "WebApi.Controllers.BooksController",
    "Method": "Delete",
    "RelativePath": "api/Books/{Id}",
    "HttpMethod": "DELETE",
    "IsController": true,
    "Order": 0,
    "Parameters": [
      {
        "Name": "Id",
        "Type": "System.Int32",
        "IsRequired": true
      }
    ],
    "ReturnTypes": []
  },
  {
    "ContainingType": "WebApi.Controllers.BooksController",
    "Method": "Get",
    "RelativePath": "api/Books/{Id}",
    "HttpMethod": "GET",
    "IsController": true,
    "Order": 0,
    "Parameters": [
      {
        "Name": "Id",
        "Type": "System.Int32",
        "IsRequired": true
      }
    ],
    "ReturnTypes": []
  },
  {
    "ContainingType": "WebApi.Controllers.IdentityController",
    "Method": "RequiredToken",
    "RelativePath": "api/Identity/RequiredToken",
    "HttpMethod": "POST",
    "IsController": true,
    "Order": 0,
    "Parameters": [
      {
        "Name": "request",
        "Type": "WebApi.Models.Identities.LoginModel",
        "IsRequired": true
      }
    ],
    "ReturnTypes": []
  },
  {
    "ContainingType": "WebApi.Controllers.PublishersController",
    "Method": "Create",
    "RelativePath": "api/Publishers",
    "HttpMethod": "POST",
    "IsController": true,
    "Order": 0,
    "Parameters": [
      {
        "Name": "createModel",
        "Type": "DataLayer.Domain.Publisher",
        "IsRequired": true
      }
    ],
    "ReturnTypes": []
  },
  {
    "ContainingType": "WebApi.Controllers.PublishersController",
    "Method": "GetAll",
    "RelativePath": "api/Publishers",
    "HttpMethod": "GET",
    "IsController": true,
    "Order": 0,
    "Parameters": [],
    "ReturnTypes": []
  },
  {
    "ContainingType": "WebApi.Controllers.PublishersController",
    "Method": "Update",
    "RelativePath": "api/Publishers",
    "HttpMethod": "PUT",
    "IsController": true,
    "Order": 0,
    "Parameters": [
      {
        "Name": "updateModel",
        "Type": "DataLayer.Domain.Publisher",
        "IsRequired": true
      }
    ],
    "ReturnTypes": []
  },
  {
    "ContainingType": "WebApi.Controllers.PublishersController",
    "Method": "Delete",
    "RelativePath": "api/Publishers/{Id}",
    "HttpMethod": "DELETE",
    "IsController": true,
    "Order": 0,
    "Parameters": [
      {
        "Name": "Id",
        "Type": "System.Int32",
        "IsRequired": true
      }
    ],
    "ReturnTypes": []
  },
  {
    "ContainingType": "WebApi.Controllers.PublishersController",
    "Method": "Get",
    "RelativePath": "api/Publishers/{Id}",
    "HttpMethod": "GET",
    "IsController": true,
    "Order": 0,
    "Parameters": [
      {
        "Name": "Id",
        "Type": "System.Int32",
        "IsRequired": true
      }
    ],
    "ReturnTypes": []
  },
  {
    "ContainingType": "WebApi.Controllers.RolesController",
    "Method": "GetAll",
    "RelativePath": "api/Roles",
    "HttpMethod": "GET",
    "IsController": true,
    "Order": 0,
    "Parameters": [],
    "ReturnTypes": []
  },
  {
    "ContainingType": "WebApi.Controllers.RolesController",
    "Method": "Create",
    "RelativePath": "api/Roles",
    "HttpMethod": "POST",
    "IsController": true,
    "Order": 0,
    "Parameters": [
      {
        "Name": "role",
        "Type": "DataLayer.Domain.AppRole",
        "IsRequired": true
      }
    ],
    "ReturnTypes": []
  },
  {
    "ContainingType": "WebApi.Controllers.RolesController",
    "Method": "Update",
    "RelativePath": "api/Roles",
    "HttpMethod": "PUT",
    "IsController": true,
    "Order": 0,
    "Parameters": [
      {
        "Name": "role",
        "Type": "DataLayer.Domain.AppRole",
        "IsRequired": true
      }
    ],
    "ReturnTypes": []
  },
  {
    "ContainingType": "WebApi.Controllers.RolesController",
    "Method": "Get",
    "RelativePath": "api/Roles/{Id}",
    "HttpMethod": "GET",
    "IsController": true,
    "Order": 0,
    "Parameters": [
      {
        "Name": "Id",
        "Type": "System.Int32",
        "IsRequired": true
      }
    ],
    "ReturnTypes": []
  },
  {
    "ContainingType": "WebApi.Controllers.RolesController",
    "Method": "Delete",
    "RelativePath": "api/Roles/{Id}",
    "HttpMethod": "DELETE",
    "IsController": true,
    "Order": 0,
    "Parameters": [
      {
        "Name": "Id",
        "Type": "System.Int32",
        "IsRequired": true
      }
    ],
    "ReturnTypes": []
  },
  {
    "ContainingType": "WebApi.Controllers.UsersController",
    "Method": "Create",
    "RelativePath": "api/Users",
    "HttpMethod": "POST",
    "IsController": true,
    "Order": 0,
    "Parameters": [
      {
        "Name": "createModel",
        "Type": "WebApi.Models.Users.CreateAppUser",
        "IsRequired": true
      }
    ],
    "ReturnTypes": []
  },
  {
    "ContainingType": "WebApi.Controllers.UsersController",
    "Method": "GetAll",
    "RelativePath": "api/Users",
    "HttpMethod": "GET",
    "IsController": true,
    "Order": 0,
    "Parameters": [],
    "ReturnTypes": []
  },
  {
    "ContainingType": "WebApi.Controllers.UsersController",
    "Method": "Update",
    "RelativePath": "api/Users",
    "HttpMethod": "PUT",
    "IsController": true,
    "Order": 0,
    "Parameters": [
      {
        "Name": "updateModel",
        "Type": "WebApi.Models.Users.UpdateAppUser",
        "IsRequired": true
      }
    ],
    "ReturnTypes": []
  },
  {
    "ContainingType": "WebApi.Controllers.UsersController",
    "Method": "Delete",
    "RelativePath": "api/Users/{Id}",
    "HttpMethod": "DELETE",
    "IsController": true,
    "Order": 0,
    "Parameters": [
      {
        "Name": "Id",
        "Type": "System.Int32",
        "IsRequired": true
      }
    ],
    "ReturnTypes": []
  },
  {
    "ContainingType": "WebApi.Controllers.UsersController",
    "Method": "Get",
    "RelativePath": "api/Users/{Id}",
    "HttpMethod": "GET",
    "IsController": true,
    "Order": 0,
    "Parameters": [
      {
        "Name": "Id",
        "Type": "System.Int32",
        "IsRequired": true
      }
    ],
    "ReturnTypes": []
  }
]